{"_id":"55ee5e446bc8676275619462","index":531,"guid":"d5bd0442-7a5b-4202-adc3-60700b16af29","isActive":false,"balance":"$20,774.55","picture":"http://placehold.it/32x32","age":34,"eyeColor":"green","name":"Jenna Cantrell","gender":"female","company":"FLOTONIC","email":"jennacantrell@flotonic.com","phone":"+1 (885) 492-3046","address":"391 Karweg Place, Matheny, Florida, 4854","about":"Proident nostrud non aliqua voluptate adipisicing fugiat deserunt labore. Sunt id sunt ex nulla non aliquip. Id nulla labore dolor ipsum mollit Lorem est elit non. Ex magna sit sunt magna sint ex tempor aliqua laboris pariatur deserunt commodo anim.\r\n","registered":"2014-05-13T03:00:11 -07:00","tags":["ex","dolor","duis","pariatur","deserunt","commodo","enim"],"friends":[{"id":0,"name":"Hart Massey"},{"id":1,"name":"Macias Holmes"},{"id":2,"name":"Hillary Kline"}],"greeting":"Hello, Jenna Cantrell! You have 3 unread messages.","favoriteFruit":"apple","location":{"latitude":-51.47225,"longitude":-140.058676},"docFormat":"json","triples":[{"triple":{"subject":"/sample-data/data-531.json","predicate":"http://www.w3.org/2000/01/rdf-schema#label","object":"Jenna Cantrell"}},{"triple":{"subject":"/sample-data/data-531.json","predicate":"http://www.w3.org/1999/02/22-rdf-syntax-ns#type","object":"http://xmlns.com/foaf/0.1/Person"}},{"triple":{"subject":"/sample-data/data-531.json","predicate":"http://xmlns.com/foaf/0.1/knows","object":"/sample-data/data-1759.json"}},{"triple":{"subject":"/sample-data/data-531.json","predicate":"http://xmlns.com/foaf/0.1/knows","object":"/sample-data/data-2325.json"}},{"triple":{"subject":"/sample-data/data-531.json","predicate":"http://xmlns.com/foaf/0.1/knows","object":"/sample-data/data-118.json"}}]}